odoo8_addon_sale_order_line_description-8.0.1.0.0.99.dev14-py3.8-nspkg.pth
odoo_addons/sale_order_line_description/README.rst
odoo_addons/sale_order_line_description/__init__.py
odoo_addons/sale_order_line_description/__openerp__.py
odoo_addons/sale_order_line_description/i18n/ca.po
odoo_addons/sale_order_line_description/i18n/de.po
odoo_addons/sale_order_line_description/i18n/es.po
odoo_addons/sale_order_line_description/i18n/fr.po
odoo_addons/sale_order_line_description/i18n/it.po
odoo_addons/sale_order_line_description/i18n/nl_NL.po
odoo_addons/sale_order_line_description/i18n/pt_BR.po
odoo_addons/sale_order_line_description/i18n/ro.po
odoo_addons/sale_order_line_description/i18n/sale_order_line_description.pot
odoo_addons/sale_order_line_description/i18n/sk.po
odoo_addons/sale_order_line_description/i18n/sl.po
odoo_addons/sale_order_line_description/i18n/tr.po
odoo_addons/sale_order_line_description/i18n/tr_TR.po
odoo_addons/sale_order_line_description/models/__init__.py
odoo_addons/sale_order_line_description/models/res_config.py
odoo_addons/sale_order_line_description/models/sale.py
odoo_addons/sale_order_line_description/security/sale_security.xml
odoo_addons/sale_order_line_description/static/description/icon.png
odoo_addons/sale_order_line_description/views/res_config_view.xml
odoo8_addon_sale_order_line_description-8.0.1.0.0.99.dev14.dist-info/METADATA
odoo8_addon_sale_order_line_description-8.0.1.0.0.99.dev14.dist-info/WHEEL
odoo8_addon_sale_order_line_description-8.0.1.0.0.99.dev14.dist-info/namespace_packages.txt
odoo8_addon_sale_order_line_description-8.0.1.0.0.99.dev14.dist-info/top_level.txt
odoo8_addon_sale_order_line_description-8.0.1.0.0.99.dev14.dist-info/RECORD
